quantum_xai/__init__.py
quantum_xai-0.1.3.dist-info/licenses/LICENSE
quantum_xai-0.1.3.dist-info/METADATA
quantum_xai-0.1.3.dist-info/WHEEL
quantum_xai-0.1.3.dist-info/top_level.txt
quantum_xai-0.1.3.dist-info/RECORD
