Metadata-Version: 2.4
Name: quantum_xai
Version: 0.1.3
Summary: Explainable Quantum Machine Learning Library for interpretable quantum models
Home-page: https://github.com/Harsha2318/QUANTUM-XAI-library
Author: Harsha P, B Manvitha Reddy
Author-email: harshagowda2318@gmail.com , manvithareddy3004@gmail.com
Classifier: Programming Language :: Python :: 3
Classifier: Operating System :: OS Independent
Requires-Python: >=3.7
License-File: LICENSE
Requires-Dist: pennylane
Requires-Dist: numpy
Requires-Dist: matplotlib
Requires-Dist: seaborn
Requires-Dist: scikit-learn
Requires-Dist: pandas
Requires-Dist: qiskit
Dynamic: author
Dynamic: author-email
Dynamic: classifier
Dynamic: description
Dynamic: description-content-type
Dynamic: home-page
Dynamic: license-file
Dynamic: requires-dist
Dynamic: requires-python
Dynamic: summary
